odoo/addons/purchase_location_by_line/README.rst
odoo/addons/purchase_location_by_line/__init__.py
odoo/addons/purchase_location_by_line/__manifest__.py
odoo/addons/purchase_location_by_line/i18n/ca.po
odoo/addons/purchase_location_by_line/i18n/de.po
odoo/addons/purchase_location_by_line/i18n/es.po
odoo/addons/purchase_location_by_line/i18n/es_MX.po
odoo/addons/purchase_location_by_line/i18n/es_PE.po
odoo/addons/purchase_location_by_line/i18n/fi.po
odoo/addons/purchase_location_by_line/i18n/fr.po
odoo/addons/purchase_location_by_line/i18n/gl.po
odoo/addons/purchase_location_by_line/i18n/hr.po
odoo/addons/purchase_location_by_line/i18n/it.po
odoo/addons/purchase_location_by_line/i18n/nl_NL.po
odoo/addons/purchase_location_by_line/i18n/pt_BR.po
odoo/addons/purchase_location_by_line/i18n/pt_PT.po
odoo/addons/purchase_location_by_line/i18n/purchase_location_by_line.pot
odoo/addons/purchase_location_by_line/i18n/ro.po
odoo/addons/purchase_location_by_line/i18n/sl.po
odoo/addons/purchase_location_by_line/models/__init__.py
odoo/addons/purchase_location_by_line/models/purchase.py
odoo/addons/purchase_location_by_line/models/stock_picking.py
odoo/addons/purchase_location_by_line/readme/CONTRIBUTORS.rst
odoo/addons/purchase_location_by_line/readme/DESCRIPTION.rst
odoo/addons/purchase_location_by_line/static/description/icon.png
odoo/addons/purchase_location_by_line/static/description/index.html
odoo/addons/purchase_location_by_line/tests/__init__.py
odoo/addons/purchase_location_by_line/tests/test_purchase_delivery.py
odoo/addons/purchase_location_by_line/views/purchase_view.xml
odoo14_addon_purchase_location_by_line-14.0.1.1.0.dist-info/METADATA
odoo14_addon_purchase_location_by_line-14.0.1.1.0.dist-info/WHEEL
odoo14_addon_purchase_location_by_line-14.0.1.1.0.dist-info/top_level.txt
odoo14_addon_purchase_location_by_line-14.0.1.1.0.dist-info/RECORD
