Metadata-Version: 2.1
Name: odoo14-addon-purchase_location_by_line
Version: 14.0.1.1.0
Summary: Allows to define a specific destination location on each PO line
Home-page: https://github.com/OCA/purchase-workflow
Author: ForgeFlow, Odoo Community Association (OCA)
Author-email: support@odoo-community.org
License: AGPL-3
Classifier: Programming Language :: Python
Classifier: Framework :: Odoo
Classifier: Framework :: Odoo :: 14.0
Classifier: License :: OSI Approved :: GNU Affero General Public License v3
Requires-Python: >=3.6
Requires-Dist: odoo14-addon-purchase-delivery-split-date
Requires-Dist: odoo<14.1dev,>=14.0a
